mmsi/__init__.py
mmsi-0.2.0.dist-info/METADATA
mmsi-0.2.0.dist-info/WHEEL
mmsi-0.2.0.dist-info/top_level.txt
mmsi-0.2.0.dist-info/RECORD
