Metadata-Version: 2.1
Name: mmsi
Version: 0.2.0
Summary: Python wrapper for Modifiable Multi-Scale Image (MMSI) library.
Home-page: https://gitlab.com/BioAI/libMI
Author: Yuxin Dong
Author-email: gamepiaynmo@gmail.com
License: UNKNOWN
Platform: UNKNOWN
Classifier: Programming Language :: Python :: 3
Classifier: License :: OSI Approved :: GNU General Public License v3 (GPLv3)
Classifier: Operating System :: OS Independent
